surface_distance/__init__.py
surface_distance/lookup_tables.py
surface_distance/metrics.py
ctg_surface_distance-0.1.dist-info/LICENSE
ctg_surface_distance-0.1.dist-info/METADATA
ctg_surface_distance-0.1.dist-info/WHEEL
ctg_surface_distance-0.1.dist-info/top_level.txt
ctg_surface_distance-0.1.dist-info/RECORD
